lrc_kit/__init__.py
lrc_kit/line.py
lrc_kit/lrc.py
lrc_kit/lyrics.py
lrc_kit/parser.py
lrc_kit/providers.py
tests/__init__.py
tests/test_individual.py
tests/test_line.py
tests/test_main.py
tests/test_parser.py
lrc_kit-0.1.8.3.dist-info/LICENSE
lrc_kit-0.1.8.3.dist-info/METADATA
lrc_kit-0.1.8.3.dist-info/WHEEL
lrc_kit-0.1.8.3.dist-info/top_level.txt
lrc_kit-0.1.8.3.dist-info/RECORD
