Metadata-Version: 2.1
Name: lrc-kit
Version: 0.1.8.3
Summary: A library to search for LRC files online and parse their contents
Home-page: https://github.com/reteps/lrc_kit
Author: Peter Stenger
Author-email: peter.promotions.stenger@gmail.com
License: UNKNOWN
Platform: UNKNOWN
Classifier: Programming Language :: Python :: 3
Classifier: License :: OSI Approved :: MIT License
Classifier: Operating System :: OS Independent
Requires-Python: >=3.6
Requires-Dist: bs4
Requires-Dist: requests
Requires-Dist: lxml
